boink/__init__.py
boink/__main__.py
boink/boink.map
boink/cdbg.py
boink/cli.py
boink/dbg.py
boink/draff.py
boink/hashing.py
boink/initializor.py
boink/libboinkCppyy.rootmap
boink/libboinkCppyy.so
boink/libboinkCppyy_rdict.pcm
boink/metadata.py
boink/options.py
boink/parsing.py
boink/processors.py
boink/serialization.py
boink/signatures.py
boink/storage.py
boink/traversal.py
boink/types.py
boink/utils.py
boink/data/__init__.py
boink/data/res_10_100_4_0.txt.gz
boink/data/res_10_110_4_0.txt.gz
boink/data/res_10_120_4_0.txt.gz
boink/data/res_10_130_4_0.txt.gz
boink/data/res_10_140_4_0.txt.gz
boink/data/res_10_150_4_0.txt.gz
boink/data/res_10_160_4_0.txt.gz
boink/data/res_10_170_4_0.txt.gz
boink/data/res_10_180_4_0.txt.gz
boink/data/res_10_190_4_0.txt.gz
boink/data/res_10_200_4_0.txt.gz
boink/data/res_10_20_4_0.txt.gz
boink/data/res_10_30_4_0.txt.gz
boink/data/res_10_40_4_0.txt.gz
boink/data/res_10_50_4_0.txt.gz
boink/data/res_10_60_4_0.txt.gz
boink/data/res_10_70_4_0.txt.gz
boink/data/res_10_80_4_0.txt.gz
boink/data/res_10_90_4_0.txt.gz
boink/data/res_7_100_4_0.txt.gz
boink/data/res_7_110_4_0.txt.gz
boink/data/res_7_120_4_0.txt.gz
boink/data/res_7_130_4_0.txt.gz
boink/data/res_7_140_4_0.txt.gz
boink/data/res_7_150_4_0.txt.gz
boink/data/res_7_160_4_0.txt.gz
boink/data/res_7_170_4_0.txt.gz
boink/data/res_7_180_4_0.txt.gz
boink/data/res_7_190_4_0.txt.gz
boink/data/res_7_200_4_0.txt.gz
boink/data/res_7_20_4_0.txt.gz
boink/data/res_7_30_4_0.txt.gz
boink/data/res_7_40_4_0.txt.gz
boink/data/res_7_50_4_0.txt.gz
boink/data/res_7_60_4_0.txt.gz
boink/data/res_7_70_4_0.txt.gz
boink/data/res_7_80_4_0.txt.gz
boink/data/res_7_90_4_0.txt.gz
boink/data/res_8_100_4_0.txt.gz
boink/data/res_8_110_4_0.txt.gz
boink/data/res_8_120_4_0.txt.gz
boink/data/res_8_130_4_0.txt.gz
boink/data/res_8_140_4_0.txt.gz
boink/data/res_8_150_4_0.txt.gz
boink/data/res_8_160_4_0.txt.gz
boink/data/res_8_170_4_0.txt.gz
boink/data/res_8_180_4_0.txt.gz
boink/data/res_8_190_4_0.txt.gz
boink-0.2.post2.dist-info/LICENSE
boink-0.2.post2.dist-info/METADATA
boink-0.2.post2.dist-info/WHEEL
boink-0.2.post2.dist-info/entry_points.txt
boink-0.2.post2.dist-info/top_level.txt
boink-0.2.post2.dist-info/RECORD
