Metadata-Version: 2.1
Name: boink
Version: 0.2.post2
Summary: boink: streaming de Bruijn graph compaction and sketching.
Home-page: UNKNOWN
Author: Camille Scott
Author-email: cswel@ucdavis.edu
License: UNKNOWN
Platform: any
Classifier: Environment :: Console
Classifier: Intended Audience :: Science/Research
Classifier: Natural Language :: English
Classifier: Operating System :: POSIX :: Linux
Classifier: Programming Language :: C++
Classifier: Programming Language :: Python :: 3.6
Classifier: Programming Language :: Python :: 3.7
Classifier: Topic :: Scientific/Engineering
Requires-Python: >=3.6
Requires-Dist: plotille
Requires-Dist: cppyy (>=1.5.5)
Requires-Dist: clang
Requires-Dist: py-cpuinfo
Requires-Dist: screed
Requires-Dist: blessings
Requires-Dist: pyfiglet
Requires-Dist: numpy
